MANIFEST.in
requirements.txt
setup.cfg
setup.py
pydirIX/__init__.py
pydirIX/dirIX.py
pydirIX/dirix.py
pydirIX.egg-info/PKG-INFO
pydirIX.egg-info/SOURCES.txt
pydirIX.egg-info/dependency_links.txt
pydirIX.egg-info/top_level.txt