Metadata-Version: 1.1
Name: pydirIX
Version: 0.2
Summary: A Python parser to the Euro-IX JSON schema for IXP member lists
Home-page: https://github.com/fooelisa/pydirix/
Author: Elisa Jasinska
Author-email: elisa@bigwaveit.org
License: UNKNOWN
Download-URL: https://github.com/fooelisa/pydirix/tarball/0.2
Keywords: IXP,Euro-IX,networking
Platform: UNKNOWN
